falcoria_common/__init__.py
falcoria_common/redis_keys.py
falcoria_common-0.1.0.dist-info/licenses/LICENSE
falcoria_common-0.1.0.dist-info/METADATA
falcoria_common-0.1.0.dist-info/WHEEL
falcoria_common-0.1.0.dist-info/top_level.txt
falcoria_common-0.1.0.dist-info/RECORD
