Metadata-Version: 2.4
Name: falcoria-common
Version: 0.1.0
Summary: Redis key builder utilities for Falcoria projects
Author-email: Sergei Gusev <gusyev.sergey@gmail.com>
License: MIT
Requires-Python: >=3.8
License-File: LICENSE
Dynamic: license-file
